infrakit/__init__.py
infrakit/cli.py
infrakit-0.1.0.dist-info/METADATA
infrakit-0.1.0.dist-info/WHEEL
infrakit-0.1.0.dist-info/entry_points.txt
infrakit-0.1.0.dist-info/top_level.txt
infrakit-0.1.0.dist-info/RECORD
