Metadata-Version: 2.1
Name: infrakit
Version: 0.1.0
Requires-Dist: click
